SamplePkg/__init__.py
SamplePkg/mymodule1.py
SamplePkg/mymodule2.py
yfirstpkg-0.3.dist-info/METADATA
yfirstpkg-0.3.dist-info/WHEEL
yfirstpkg-0.3.dist-info/top_level.txt
yfirstpkg-0.3.dist-info/RECORD
